{
    "700000100": "NOCTURNA MARÍA ELISA RUFINO LEÓN",
    "700000101": "ANEXO NOCTURNA MARÍA ELISA RUFINO LEÓN",
    "700000200": "MARIANO NECOCHEA T.M.",
    "700000300": "NOCTURNA TOMAS ALVA EDISON",
    "700000400": "JUAN ANTOLÍN ZAPATA",
    "700000500": "VALLE DE TULUM",
    "700000600": "NOCTURNA PRIMERA JUNTA",
    "700000700": "FRANCISCO DE VILLAGRA",
    "700000800": "ESCUELA JUAN DOLORES GODOY",
    "700000900": "C.E.N.S. N°348 MADRE TERESA DE CALCUTA",
    "700001400": "E.P.E.T. N°6 LA BEBIDA",
    "700001500": "GENERAL DE LA NACIÓN INGENIERO ENRIQUE MOSCONI",
    "700001800": "NOCTURNA ÁNGEL SALVADOR MARTÍN",
    "700001801": "ESCUELA NOCTURNA ÁNGEL SAN MARTÍN - ANEXO VILLA HIPÓDROMO",
    "700001900": "JUAN XXIII",
    "700002000": "ESCUELA NOCTURNA ALMIRANTE BROWN",
    "700002001": "ANEXO ESCUELA NOCTURNA ALMIRANTE BROWN",
    "700002100": "ESCUELA GABRIELA MISTRAL",
    "700002200": "JOSÉ HERNÁNDEZ",
    "700002300": "LUIS JORGE FONTANA",
    "700002400": "JINZ CAPITAL LUIS JORGE FONTANA",
    "700002401": "JINZ CAPITAL ESCUELA PROVINCIA DE BUENOS AIRES",
    "700002403": "JINZ CAPITAL ESCUELA PROVINCIA DE SANTIAGO DEL ESTERO",
    "700002404": "JINZ CAPITAL ESCUELA PEDRO NOLASCO FONSECA",
    "700002500": "MANUEL BELGRANO",
    "700002600": "ESCUELA DE EDUCACIÓN INICIAL ENI N°1 FEDERICO FROEBEL",
    "700002800": "COLEGIO SECUNDARIO GENERAL TORIBIO DE LUZURIAGA",
    "700003000": "CLARA ROSA CORTÍNEZ",
    "700003300": "GENERAL MARIANO ACHA",
    "700003400": "JOSÉ MARÍA TORRES",
    "700003500": "ESCUELA DE NIVEL INICIAL ENI N°7 AYAC YANEN",
    "700003600": "WERFIELD SALINAS",
    "700003900": "PROVINCIA DE LA RIOJA",
    "700004000": "COLEGIO DOCTOR MANUEL ALVAR LOPEZ (CHIMBASII)",
    "700004200": "INGENIEROS DE SAN JUAN",
    "700004300": "U.E.P.A. MOVIL N°14",
    "700004400": "ESCUELA NOCTURNA JOSÉ MANUEL ESTRADA",
    "700004401": "ESCUELA NOCTURNA JOSÉ MANUEL ESTRADA ANEXO BERMEJO",
    "700004402": "ESCUELA NOCTURNA JOSÉ MANUEL ESTRADA ANEXO VILLA INDEPENDENCIA",
    "700004500": "ESCUELA DE NIVEL INICIAL ENI N°11 MARTA GIMÉNEZ PASTOR",
    "700004600": "CANDELARIA ALBARRACÍN DE GODOY",
    "700004700": "ANTONIO DE LA TORRE",
    "700004800": "C.E.N.S. N°134",
    "700004900": "ALAS ARGENTINAS",
    "700005000": "ESCCUELA EDUCACIÓN ESPECIAL DRA. CAROLINA TOBAR GARCÍA",
    "700005100": "U.E.P.A. N°9",
    "700005300": "COLEGIO SECUNDARIO CAPITÁN DE FRAGATA CARLOS MARIA MOYANO",
    "700005400": "SAN JUAN EUDES",
    "700005500": "EUGENIA BELÍN SARMIENTO",
    "700005600": "C.E.N.S. N°249",
    "700005700": "ADÁN QUIROGA",
    "700005800": "BENITA DÁVILA de DE LOS RÍOS",
    "700006200": "NOCTURNA INGENIERO LUIS ÁNGEL NOUSSAN",
    "700006300": "CARLOS MARIA DE ALVEAR TURNO TARDE",
    "700006500": "TENIENTE GENERAL PEDRO EUGENIO ARAMBURU TURNO MAÑANA",
    "700006600": "JUAN JOSÉ DE VERTIZ",
    "700006700": "YAPEYÚ",
    "700006800": "17 DE AGOSTO",
    "700006900": "MANUEL ALBERTI"
}
